randomword/__init__.py
randomword-1.0.2.dist-info/LICENSE
randomword-1.0.2.dist-info/METADATA
randomword-1.0.2.dist-info/WHEEL
randomword-1.0.2.dist-info/top_level.txt
randomword-1.0.2.dist-info/RECORD
