Metadata-Version: 2.1
Name: randomword
Version: 1.0.2
Summary: A simple python library that gives you a certain amount of random words.
Home-page: https://github.com/Hexiro/randomword/
Author: Hexiro
Author-email: realhexiro@gmail.com
License: MIT
Platform: UNKNOWN
Requires-Python: >=3.6
